SumOfSquares/SoS.py
SumOfSquares/__init__.py
SumOfSquares/basis.py
SumOfSquares/util.py
SumOfSquares-1.3.1.dist-info/LICENSE
SumOfSquares-1.3.1.dist-info/METADATA
SumOfSquares-1.3.1.dist-info/WHEEL
SumOfSquares-1.3.1.dist-info/top_level.txt
SumOfSquares-1.3.1.dist-info/RECORD
