Metadata-Version: 2.1
Name: SumOfSquares
Version: 1.3.1
Summary: Python implementation of Sum-of-Squares optimization built on picos
Author-email: Chenyang Yuan <yuanchenyang@gmail.com>
Maintainer-email: Chenyang Yuan <yuanchenyang@gmail.com>
License: Copyright 2020-2024 Chenyang Yuan
Project-URL: Homepage, https://github.com/yuanchenyang/SumOfSquares.py
Project-URL: Bug Tracker, https://github.com/yuanchenyang/SumOfSquares.py/issues
Project-URL: Documentation, https://sums-of-squares.github.io/sos/index.html#python
Project-URL: Source, https://github.com/yuanchenyang/SumOfSquares.py
Classifier: Development Status :: 4 - Beta
Classifier: License :: OSI Approved :: MIT License
Classifier: Programming Language :: Python :: 3
Classifier: Operating System :: OS Independent
Requires-Python: >=3.7
License-File: LICENSE
Requires-Dist: numpy
Requires-Dist: sympy
Requires-Dist: picos
Provides-Extra: convexhull
Requires-Dist: scipy ; extra == 'convexhull'
Provides-Extra: dev
Requires-Dist: build ; extra == 'dev'
Requires-Dist: twine ; extra == 'dev'
Provides-Extra: test
Requires-Dist: pytest ; extra == 'test'
Requires-Dist: pytest-cov ; extra == 'test'
